labportalen/__init__.py
labportalen/admin.py
labportalen/apps.py
labportalen/constants.py
labportalen/models.py
labportalen/services.py
labportalen/tests.py
labportalen/urls.py
labportalen/api/serializers.py
labportalen/api/services.py
labportalen/api/urls.py
labportalen/api/views.py
labportalen/migrations/0001_initial.py
labportalen/migrations/0002_alter_lab_lab_code.py
labportalen/migrations/__init__.py
labportalen/migrations/__pycache__/0001_initial.cpython-39.pyc
labportalen/migrations/__pycache__/0002_alter_lab_lab_code.cpython-39.pyc
labportalen/migrations/__pycache__/__init__.cpython-39.pyc
labportalen/sample_report/HKV_result_2.xml
labportalen/soap_service/client.py
labportalen/soap_service/services.py
django_labportalen-0.0.33.dist-info/LICENSE
django_labportalen-0.0.33.dist-info/METADATA
django_labportalen-0.0.33.dist-info/WHEEL
django_labportalen-0.0.33.dist-info/top_level.txt
django_labportalen-0.0.33.dist-info/RECORD
