Metadata-Version: 2.1
Name: django-labportalen
Version: 0.0.33
Summary: A Django app to communicate with Swedish Labportalen. Suitable with eRemiss <= 3.1.0
Home-page: https://github.com/strativ-dev/django-labportalen
Author: Md. Badiuzzaman Pranto
Author-email: prantoamt@gmail.com
License: MIT License
Classifier: Environment :: Web Environment
Classifier: Framework :: Django
Classifier: Framework :: Django :: 3.2
Classifier: Intended Audience :: Developers
Classifier: License :: OSI Approved :: MIT License
Classifier: Operating System :: OS Independent
Classifier: Programming Language :: Python
Classifier: Programming Language :: Python :: 3
Classifier: Programming Language :: Python :: 3 :: Only
Classifier: Programming Language :: Python :: 3.6
Classifier: Programming Language :: Python :: 3.7
Classifier: Programming Language :: Python :: 3.8
Classifier: Topic :: Internet :: WWW/HTTP
Classifier: Topic :: Internet :: WWW/HTTP :: Dynamic Content
Requires-Python: >=3.8
License-File: LICENSE
Requires-Dist: coreapi (>=2.3.3)
Requires-Dist: coreschema (>=0.0.4)
Requires-Dist: Django (>=3.2.9)
Requires-Dist: django-cors-headers (>=3.10.0)
Requires-Dist: djangorestframework (>=3.12.4)
Requires-Dist: Markdown (>=3.3.6)
Requires-Dist: MarkupSafe (>=2.0.1)
Requires-Dist: psycopg2-binary (>=2.9.2)
Requires-Dist: pysftp (>=0.2.9)
Requires-Dist: xmltodict (>=0.12.0)
Requires-Dist: zeep (>=3.4.0)
